[
null,
{"id":1,"autoRemovalTiming":0,"chanceByDamage":100,"iconIndex":0,"maxTurns":1,"message1":"","message2":"を倒した！","message3":"","message4":"は立ち上がった！","minTurns":1,"motion":0,"overlay":0,"name":"戦闘不能","note":"ステート１番はＨＰが０になったときに自動的に付加されます。","priority":100,"removeAtBattleEnd":false,"removeByDamage":false,"removeByRestriction":false,"removeByWalking":false,"restriction":4,"stepsToRemove":100,"traits":[{"code":23,"dataId":9,"value":0}]},
{"id":2,"autoRemovalTiming":0,"chanceByDamage":100,"iconIndex":0,"maxTurns":1,"message1":"","message2":"","message3":"","message4":"","minTurns":1,"motion":0,"overlay":0,"name":"毒","note":"","priority":50,"removeAtBattleEnd":false,"removeByDamage":false,"removeByRestriction":false,"removeByWalking":false,"restriction":0,"stepsToRemove":100,"traits":[{"code":22,"dataId":7,"value":-0.2}]}
]